{"Bi6dr64y6+dUpWyQJkHAvg==":"rockbrush-128x128.png","HhwfgITZePxYkqipCUK+DQ==":"arcadewreckage-2000x1545.png","uU5NxGW4IBP3lnY6NPMHQg==":"4153821-natural-background-texture-of-green-leaf-2000x1332.jpg","U9L1jBwywXb4CM6dXWqy2g==":"leaves_texture1947-2000x1332.jpg","BgRk3iZcV9RKIt6elcPIAg==":"lilypad+web-112x128.jpg","JMnPFSl1iBFFOefEtS6l3w==":"richbdaycard-2000x1500.jpg","cybi70Q2gFtvAoagSV5HjQ==":"bike-2000x1545.png","pmVwmVfPTcSvMzOWJUkMuw==":"5535087-170x128.png","cMH6rLKJdRpV/3PvzNrSig==":"20161015-2000x1500.jpg","lCthp868w9KyJgCXY7m3+A==":"20161206-1400x1050.jpg","jm+cwzy5UHzSPqqCVRTl3Q==":"20161015-1400x1050.jpg","sMiDz6ZJiv8n4R9fIQg5gQ==":"20161015-1-1400x1050.jpg","Lcj35xzGt5IhunP0Q8MglQ==":"20161206-1-1400x1050.jpg","uUh7vIOYmwrOeYRIJH7oDQ==":"hinh-anh-ngoi-sao-ky-la-sang-gap-300-lan-mat-troi.gif","xkM3YVSHucmHmSm+31q/lg==":"5535087-128x96.png","uv/0iGWVEF24PwIfjPtpdw==":"20161015-1-2000x1500.jpg","v5/E5ViKPYOjB3TxvyGn+Q==":"depositphotos_1630557-stock-photo-leaf-texture-2000x1644.jpg","/5Zg0PgVqrg2RFt5F4UJJQ==":"55350876x5-170x128.png","Zzy8l60g+wJRE9WsEV0igA==":"55350876x5-128x96.png","i/F1INOaZxlKf+Vq3JxzYA==":"mbr-1400x989.jpg","ZMW/Qhrchs59PzXlOSbO2Q==":"mbr-2000x1125.jpg","NlJRAKUqb7GJNXoXLzx84Q==":"mbr-2000x1330.jpg","RLS5QUfLcBLRwPePY86iZA==":"mbr-2000x1500.jpg","h9NRQKAb7CqC8EOIdIGMhQ==":"sketch-2000x1333.png","eRLD4wNueDHoENfgpeHJBQ==":"tune%20in-1654x2339.png","sw/p5+Z1hJJ+rpX0XCgYqg==":"sketch%20(2)-1400x933.png","Ik8LBXovNBdjXoLKt2kJzA==":"sketch%20(3)-1400x933.png","wqoKva+Mxsvp15ly3ASUOA==":"mbr-1620x1080.jpg","9O0nrg5yyG2d2rY/IIab1Q==":"mbr-720x1080.jpg","HyztMLpTjvKUVUnAKImIVw==":"mbr-864x1080.jpg","V3K61y2B57rdzNtKnzZqnA==":"mbr-1620x1080.jpg","Vfq2qNVcgEvEodv0UplsXw==":"mbr-1920x1053.jpg","fsQp4uE/A6L7mCB6zMr9pQ==":"mbr-1-1620x1080.jpg","0y7F4pjC+k1wm5wkv2c8KA==":"slide3-1600x900.jpg","vW1pqy7/vmJtQkE67u9UEw==":"20171117-63227-1400x1050.jpg","SLeyN3QgekQLoyMaqNvteQ==":"20171120-140552-1078x606.jpg","l1xSNCZw9+ghfKpgzc0uDA==":"20171220-33221-1400x1050.jpg","HBZIx4On7XxMWkmpwx4Flg==":"2018-02-5-2000x1333.png","6cxROZiQcpNIBEUXd6xHSA==":"mbr-715x1080.jpg","bd9sAlShXzSd2m0z4JJrGA==":"mbr-1619x1080.jpg","e8/mzYpeVflPfm+jZUWTrg==":"mbr-1618x1080.jpg","gjSntbPbi+vv6ScpCNQykA==":"aflappsitemap-800x800.png","9aeC8RpVw/TQ3hznNjKRwA==":"aflappsitemap2-800x800.png","ldRbjxw20yMdy4TjRmZdlg==":"olddudesketch-800x800.png","7b0+Ehg+CPeaHyjt3jhD+A==":"ods2-800x800.png","jSBljTul2HksZQY9aYZhUQ==":"me3scover-2000x1500.png","kxCtEdgWRvXvoMbb0trDqA==":"mbr-2-1620x1080.jpg"}